refind/__init__.py
refind/__main__.py
refind/find.py
refind-1.0.7.dist-info/LICENSE.md
refind-1.0.7.dist-info/METADATA
refind-1.0.7.dist-info/WHEEL
refind-1.0.7.dist-info/entry_points.txt
refind-1.0.7.dist-info/top_level.txt
refind-1.0.7.dist-info/RECORD
